firefly/__init__.py
firefly/__main__.py
firefly/index.html
firefly/main.py
firefly/server.py
firefly/bin/firefly
firefly/bin/firefly_bash
firefly/bin/firefly_launcher
firefly/bin/make_new_repo.sh
firefly/data_reader/FIREreader.py
firefly/data_reader/GAIAreader.py
firefly/data_reader/__init__.py
firefly/data_reader/binary_writer.py
firefly/data_reader/json_utils.py
firefly/data_reader/octree.py
firefly/data_reader/particlegroup.py
firefly/data_reader/reader.py
firefly/data_reader/settings.py
firefly/data_reader/tween.py
firefly/data_reader/kaitai_io/firefly.ksy
firefly/data_reader/kaitai_io/my_array_buffer.ksy
firefly/data_reader/kaitai_io/node.ksy
firefly/data_reader/kaitai_io/raw_array.ksy
firefly/data_reader/kaitai_io/test.b
firefly/ntbks/GaiaDR3.ipynb
firefly/ntbks/convert_FIRE_data.ipynb
firefly/ntbks/flask_tutorial.ipynb
firefly/ntbks/memoryScaling.ipynb
firefly/ntbks/minimal_example.ipynb
firefly/ntbks/minimal_example_electron.ipynb
firefly/ntbks/multiple_datasets_tutorial.ipynb
firefly/ntbks/octree_test.ipynb
firefly/ntbks/passing_settings.ipynb
firefly/ntbks/performance_testing.ipynb
firefly/ntbks/reader_tutorial.ipynb
firefly/ntbks/selecting_data.ipynb
firefly/ntbks/settings_tutorial.ipynb
firefly/ntbks/examples/DiskFormation.ipynb
firefly/ntbks/examples/GaiaDR3_octree.ipynb
firefly/ntbks/examples/GaiaDR3toFirefly.ipynb
firefly/ntbks/examples/SDSS_test.ipynb
firefly/ntbks/py_conversions/convert_FIRE_data.py
firefly/ntbks/py_conversions/flask_tutorial.py
firefly/ntbks/py_conversions/minimal_example.py
firefly/ntbks/py_conversions/multiple_datasets_tutorial.py
firefly/ntbks/py_conversions/reader_tutorial.py
firefly/ntbks/py_conversions/settings_tutorial.py
firefly/static/css/UIStyles.css
firefly/static/css/UIStyles2.css
firefly/static/css/mainStyles.css
firefly/static/data/startup.json
firefly/static/docs/FIREFLY-02_trimmed.png
firefly/static/docs/GUIicon.png
firefly/static/docs/README.md
firefly/static/docs/READMEcleanPack.md
firefly/static/docs/UI.png
firefly-3.4.1.dist-info/licenses/LICENSE
firefly-3.4.1.dist-info/METADATA
firefly-3.4.1.dist-info/WHEEL
firefly-3.4.1.dist-info/top_level.txt
firefly-3.4.1.dist-info/RECORD
