Metadata-Version: 2.4
Name: firefly
Version: 3.4.1
Summary: A browser-based particle visualization platform
Home-page: https://firefly.rcs.northwestern.edu/
Author: Alex Gurvich, Aaron Geller
Author-email: alex.b.gurvich@gmail.com, a-geller@northwestern.edu
Project-URL: Bug Tracker, https://github.com/ageller/Firefly/issues
Classifier: Programming Language :: Python :: 3
Classifier: License :: OSI Approved :: GNU Affero General Public License v3 or later (AGPLv3+)
Classifier: Operating System :: OS Independent
Requires-Python: >=3.6
License-File: LICENSE
Requires-Dist: numpy
Requires-Dist: h5py
Requires-Dist: pandas
Requires-Dist: eventlet
Requires-Dist: flask-socketio
Requires-Dist: flask
Requires-Dist: requests
Requires-Dist: abg_python>=1.1.1
Dynamic: author
Dynamic: author-email
Dynamic: classifier
Dynamic: description
Dynamic: description-content-type
Dynamic: home-page
Dynamic: license-file
Dynamic: project-url
Dynamic: requires-dist
Dynamic: requires-python
Dynamic: summary
